podman_hpc/__init__.py
podman_hpc/argparse_exit_on_error.py
podman_hpc/click_passthrough.py
podman_hpc/configure_hooks.py
podman_hpc/hook_tool.py
podman_hpc/migrate2scratch.py
podman_hpc/podman_hpc.py
podman_hpc/siteconfig.py
podman_hpc-1.1.4.data/data/etc/podman_hpc/01-cvmfs.conf
podman_hpc-1.1.4.data/data/etc/podman_hpc/01-gpu.conf
podman_hpc-1.1.4.data/data/etc/podman_hpc/01-mpich.conf
podman_hpc-1.1.4.data/data/etc/podman_hpc/01-nccl.conf
podman_hpc-1.1.4.data/data/etc/podman_hpc/podman_hpc.yaml
podman_hpc-1.1.4.data/data/etc/podman_hpc/modules.d/cfs.yaml
podman_hpc-1.1.4.data/data/etc/podman_hpc/modules.d/cuda-mpich.yaml
podman_hpc-1.1.4.data/data/etc/podman_hpc/modules.d/cvmfs.yaml
podman_hpc-1.1.4.data/data/etc/podman_hpc/modules.d/gpu.yaml
podman_hpc-1.1.4.data/data/etc/podman_hpc/modules.d/home.yaml
podman_hpc-1.1.4.data/data/etc/podman_hpc/modules.d/jupyter.yaml
podman_hpc-1.1.4.data/data/etc/podman_hpc/modules.d/mpich.yaml
podman_hpc-1.1.4.data/data/etc/podman_hpc/modules.d/nccl.yaml
podman_hpc-1.1.4.data/data/etc/podman_hpc/modules.d/openmpi-pmi2.yaml
podman_hpc-1.1.4.data/data/etc/podman_hpc/modules.d/openmpi-pmix.yaml
podman_hpc-1.1.4.data/data/etc/podman_hpc/modules.d/scratch.yaml
podman_hpc-1.1.4.data/scripts/fuse-overlayfs-wrap
podman_hpc-1.1.4.dist-info/LICENSE
podman_hpc-1.1.4.dist-info/METADATA
podman_hpc-1.1.4.dist-info/WHEEL
podman_hpc-1.1.4.dist-info/entry_points.txt
podman_hpc-1.1.4.dist-info/top_level.txt
podman_hpc-1.1.4.dist-info/RECORD
