Metadata-Version: 2.1
Name: podman-hpc
Version: 1.1.4
Summary: UNKNOWN
Home-page: UNKNOWN
License: UNKNOWN
Platform: UNKNOWN
License-File: LICENSE
Requires-Dist: toml
Requires-Dist: pyyaml
Requires-Dist: click
